reVReports/__init__.py
reVReports/_version.py
reVReports/characterizations.py
reVReports/cli.py
reVReports/configs.py
reVReports/data.py
reVReports/exceptions.py
reVReports/fonts.py
reVReports/logs.py
reVReports/maps.py
reVReports/plots.py
reVReports/assets/LocalDejaVuSans-Bold.ttf
reVReports/assets/LocalDejaVuSans.ttf
reVReports/datasets/ne_50m_admin_1_states_provinces_lakes_conus.geojson
reVReports/utilities/__init__.py
reVReports/utilities/maps.py
reVReports/utilities/plots.py
revreports-1.1.0.dist-info/licenses/LICENSE
revreports-1.1.0.dist-info/METADATA
revreports-1.1.0.dist-info/WHEEL
revreports-1.1.0.dist-info/entry_points.txt
revreports-1.1.0.dist-info/top_level.txt
revreports-1.1.0.dist-info/RECORD
